[{"name":"_ga_M6V9BEQD2J","value":"GS1.1.1666116197.1.1.1666116456.0.0.0","domain":".todoist.com","path":"/","expires":1700676456.051375,"size":51,"httpOnly":false,"secure":false,"session":false,"sameParty":false,"sourceScheme":"Secure","sourcePort":443},{"name":"_dd_s","value":"logs=1&id=34f44df7-8bd0-429f-a5f7-a26b14516455&created=1666116197635&expire=1666117355784","domain":"todoist.com","path":"/","expires":1666117355,"size":94,"httpOnly":false,"secure":false,"session":false,"sameSite":"Strict","sameParty":false,"sourceScheme":"Secure","sourcePort":443},{"name":"_ga","value":"GA1.1.1843232163.1666116198","domain":".todoist.com","path":"/","expires":1700676456.044616,"size":30,"httpOnly":false,"secure":false,"session":false,"sameParty":false,"sourceScheme":"Secure","sourcePort":443}]